pyexcel_pygal/__init__.py
pyexcel_pygal/chart.py
pyexcel_pygal-0.0.2.dist-info/DESCRIPTION.rst
pyexcel_pygal-0.0.2.dist-info/METADATA
pyexcel_pygal-0.0.2.dist-info/RECORD
pyexcel_pygal-0.0.2.dist-info/WHEEL
pyexcel_pygal-0.0.2.dist-info/metadata.json
pyexcel_pygal-0.0.2.dist-info/top_level.txt
