Metadata-Version: 1.1
Name: pyexcel-pygal
Version: 0.0.2
Summary: draw simple svg chart via pygal
Home-page: https://github.com/pyexcel-renderers/pyexcel-pygal
Author: C.W.
Author-email: wangc_2011@hotmail.com
License: New BSD
Download-URL: https://github.com/pyexcel-renderers/pyexcel-pygal/archive/0.0.2.tar.gz
Keywords: python
Platform: UNKNOWN
Classifier: Topic :: Office/Business
Classifier: Topic :: Utilities
Classifier: Topic :: Software Development :: Libraries
Classifier: Programming Language :: Python
Classifier: Intended Audience :: Developers
Classifier: Programming Language :: Python :: 2.6
Classifier: Programming Language :: Python :: 2.7
Classifier: Programming Language :: Python :: 3.3
Classifier: Programming Language :: Python :: 3.4
Classifier: Programming Language :: Python :: 3.5
Classifier: Programming Language :: Python :: 3.6
Classifier: License :: OSI Approved :: BSD License
